tutbot.py
tutbot-0.0.1.0.dist-info/WHEEL
tutbot-0.0.1.0.dist-info/METADATA
tutbot-0.0.1.0.dist-info/RECORD
