Metadata-Version: 2.1
Name: tutbot
Version: 0.0.1.0
Summary: 在TuT使用Py接入HTTPAPI
Author-email: "Luo.yu_u-520" <luoyu_u@qq.com>
